README
setup.py
active_redis/__init__.py
active_redis/active_redis.py
active_redis/active_redis_model.py
active_redis/pluralize_engine.py
active_redis/uuid_generator.py
active_redis.egg-info/PKG-INFO
active_redis.egg-info/SOURCES.txt
active_redis.egg-info/dependency_links.txt
active_redis.egg-info/requires.txt
active_redis.egg-info/top_level.txt