Metadata-Version: 1.0
Name: active-redis
Version: 0.0.1
Summary: Simple ActiveRecord pattern for Redis
Home-page: http://github.com/PagedeGeek/active_redis
Author: Samuel Sanchez
Author-email: samuel@pagedegeek.com
License: UNKNOWN
Keywords: Redis ActiveRecord
Platform: UNKNOWN
